CHANGES.rst
LICENSE
MANIFEST.in
README.rst
package.json
setup.cfg
setup.py
tox.ini
webpack.config.js
client/controller.js
client/index.html
client/main.js
client/styles.css
client/components/App/index.js
client/components/Footer/index.js
client/components/List/index.js
client/components/NewTodo/index.js
client/components/Todo/index.js
client/computed/counts.js
client/computed/isAllChecked.js
client/computed/visibleTodosRefs.js
client/modules/app/index.js
client/modules/app/actions/clearCompletedTodos.js
client/modules/app/actions/createTodo.js
client/modules/app/actions/deleteCompletedTodos.js
client/modules/app/actions/deleteTodo.js
client/modules/app/actions/editTodo.js
client/modules/app/actions/getCompletedTodos.js
client/modules/app/actions/getTodos.js
client/modules/app/actions/markTodoFailed.js
client/modules/app/actions/overwriteTodoTitle.js
client/modules/app/actions/postTodo.js
client/modules/app/actions/prepareToggleAll.js
client/modules/app/actions/putTodo.js
client/modules/app/actions/putToggleAll.js
client/modules/app/actions/removeTodo.js
client/modules/app/actions/setFilter.js
client/modules/app/actions/setTodoNewTitle.js
client/modules/app/actions/setTodos.js
client/modules/app/actions/stopEditingTodo.js
client/modules/app/actions/toggleAllChecked.js
client/modules/app/actions/toggleTodoCompleted.js
client/modules/app/actions/updateTodo.js
client/modules/app/chains/clearCompletedTodos.js
client/modules/app/chains/editTodo.js
client/modules/app/chains/overwriteTodoTitle.js
client/modules/app/chains/redirectToAll.js
client/modules/app/chains/removeTodo.js
client/modules/app/chains/setFilter.js
client/modules/app/chains/setTitle.js
client/modules/app/chains/setTodoNewTitle.js
client/modules/app/chains/setTodos.js
client/modules/app/chains/stopEditingTodo.js
client/modules/app/chains/submitTodo.js
client/modules/app/chains/toggleAllChecked.js
client/modules/app/chains/toggleTodoCompleted.js
client/modules/app/factories/notifyError.js
morepath_cerebral_todomvc.egg-info/PKG-INFO
morepath_cerebral_todomvc.egg-info/SOURCES.txt
morepath_cerebral_todomvc.egg-info/dependency_links.txt
morepath_cerebral_todomvc.egg-info/entry_points.txt
morepath_cerebral_todomvc.egg-info/not-zip-safe
morepath_cerebral_todomvc.egg-info/requires.txt
morepath_cerebral_todomvc.egg-info/top_level.txt
server/__init__.py
