Metadata-Version: 1.1
Name: morepath-cerebral-todomvc
Version: 0.2
Summary: Morepath example of using React & Cerebral
Home-page: https://github.com/morepath/morepath_cerebral_todomvc
Author: Morepath developers
Author-email: morepath@googlegroups.com
License: BSD
Platform: any
Classifier: Intended Audience :: Developers
Classifier: Environment :: Web Environment
Classifier: License :: OSI Approved :: BSD License
Classifier: Topic :: Internet :: WWW/HTTP :: WSGI
Classifier: Programming Language :: Python :: 2.7
Classifier: Programming Language :: Python :: 3.4
Classifier: Programming Language :: Python :: 3.5
